[
  {
    "id": "frag-72084",
    "name": "",
    "brand": "",
    "slug": "",
    "year": null,
    "gender": null,
    "fragrance_family": null,
    "concentration": null,
    "description": "",
    "fragrantica_url": "https://www.fragrantica.com/perfume/AAP-PERFUMES/ADAM-72084.html",
    "fragrantica_rating": 0,
    "fragrantica_votes": 0,
    "main_accords": [],
    "top_notes": [],
    "heart_notes": [],
    "base_notes": [],
    "longevity": 0,
    "sillage": 0,
    "season_performance": null,
    "image_url": "/images/fragrances/72084.jpg",
    "brand_logo_url": null,
    "similar_scents": []
  },
  {
    "id": "frag-72080",
    "name": "",
    "brand": "",
    "slug": "",
    "year": null,
    "gender": null,
    "fragrance_family": null,
    "concentration": null,
    "description": "",
    "fragrantica_url": "https://www.fragrantica.com/perfume/AAP-PERFUMES/BALSAMIC-CACAO-72080.html",
    "fragrantica_rating": 0,
    "fragrantica_votes": 0,
    "main_accords": [],
    "top_notes": [],
    "heart_notes": [],
    "base_notes": [],
    "longevity": 0,
    "sillage": 0,
    "season_performance": null,
    "image_url": "/images/fragrances/72080.jpg",
    "brand_logo_url": null,
    "similar_scents": []
  },
  {
    "id": "frag-72075",
    "name": "",
    "brand": "",
    "slug": "",
    "year": null,
    "gender": null,
    "fragrance_family": null,
    "concentration": null,
    "description": "",
    "fragrantica_url": "https://www.fragrantica.com/perfume/AAP-PERFUMES/COCONUT-BERGAMOT-72075.html",
    "fragrantica_rating": 0,
    "fragrantica_votes": 0,
    "main_accords": [],
    "top_notes": [],
    "heart_notes": [],
    "base_notes": [],
    "longevity": 0,
    "sillage": 0,
    "season_performance": null,
    "image_url": "/images/fragrances/72075.jpg",
    "brand_logo_url": null,
    "similar_scents": []
  },
  {
    "id": "frag-72072",
    "name": "",
    "brand": "",
    "slug": "",
    "year": null,
    "gender": null,
    "fragrance_family": null,
    "concentration": null,
    "description": "",
    "fragrantica_url": "https://www.fragrantica.com/perfume/AAP-PERFUMES/FRESH-SPICY-72072.html",
    "fragrantica_rating": 0,
    "fragrantica_votes": 0,
    "main_accords": [],
    "top_notes": [],
    "heart_notes": [],
    "base_notes": [],
    "longevity": 0,
    "sillage": 0,
    "season_performance": null,
    "image_url": "/images/fragrances/72072.jpg",
    "brand_logo_url": null,
    "similar_scents": []
  },
  {
    "id": "frag-72082",
    "name": "",
    "brand": "",
    "slug": "",
    "year": null,
    "gender": null,
    "fragrance_family": null,
    "concentration": null,
    "description": "",
    "fragrantica_url": "https://www.fragrantica.com/perfume/AAP-PERFUMES/IRIS-AMBER-72082.html",
    "fragrantica_rating": 0,
    "fragrantica_votes": 0,
    "main_accords": [],
    "top_notes": [],
    "heart_notes": [],
    "base_notes": [],
    "longevity": 0,
    "sillage": 0,
    "season_performance": null,
    "image_url": "/images/fragrances/72082.jpg",
    "brand_logo_url": null,
    "similar_scents": []
  },
  {
    "id": "frag-72078",
    "name": "",
    "brand": "",
    "slug": "",
    "year": null,
    "gender": null,
    "fragrance_family": null,
    "concentration": null,
    "description": "",
    "fragrantica_url": "https://www.fragrantica.com/perfume/AAP-PERFUMES/LILY-OF-THE-VALLEY-72078.html",
    "fragrantica_rating": 0,
    "fragrantica_votes": 0,
    "main_accords": [],
    "top_notes": [],
    "heart_notes": [],
    "base_notes": [],
    "longevity": 0,
    "sillage": 0,
    "season_performance": null,
    "image_url": "/images/fragrances/72078.jpg",
    "brand_logo_url": null,
    "similar_scents": []
  },
  {
    "id": "frag-72079",
    "name": "",
    "brand": "",
    "slug": "",
    "year": null,
    "gender": null,
    "fragrance_family": null,
    "concentration": null,
    "description": "",
    "fragrantica_url": "https://www.fragrantica.com/perfume/AAP-PERFUMES/MYSTERIES-OF-WOOD-72079.html",
    "fragrantica_rating": 0,
    "fragrantica_votes": 0,
    "main_accords": [],
    "top_notes": [],
    "heart_notes": [],
    "base_notes": [],
    "longevity": 0,
    "sillage": 0,
    "season_performance": null,
    "image_url": "/images/fragrances/72079.jpg",
    "brand_logo_url": null,
    "similar_scents": []
  },
  {
    "id": "frag-72073",
    "name": "",
    "brand": "",
    "slug": "",
    "year": null,
    "gender": null,
    "fragrance_family": null,
    "concentration": null,
    "description": "",
    "fragrantica_url": "https://www.fragrantica.com/perfume/AAP-PERFUMES/NUTMEG-HONEY-72073.html",
    "fragrantica_rating": 0,
    "fragrantica_votes": 0,
    "main_accords": [],
    "top_notes": [],
    "heart_notes": [],
    "base_notes": [],
    "longevity": 0,
    "sillage": 0,
    "season_performance": null,
    "image_url": "/images/fragrances/72073.jpg",
    "brand_logo_url": null,
    "similar_scents": []
  },
  {
    "id": "frag-72077",
    "name": "",
    "brand": "",
    "slug": "",
    "year": null,
    "gender": null,
    "fragrance_family": null,
    "concentration": null,
    "description": "",
    "fragrantica_url": "https://www.fragrantica.com/perfume/AAP-PERFUMES/OAKMOSS-72077.html",
    "fragrantica_rating": 0,
    "fragrantica_votes": 0,
    "main_accords": [],
    "top_notes": [],
    "heart_notes": [],
    "base_notes": [],
    "longevity": 0,
    "sillage": 0,
    "season_performance": null,
    "image_url": "/images/fragrances/72077.jpg",
    "brand_logo_url": null,
    "similar_scents": []
  },
  {
    "id": "frag-72076",
    "name": "",
    "brand": "",
    "slug": "",
    "year": null,
    "gender": null,
    "fragrance_family": null,
    "concentration": null,
    "description": "",
    "fragrantica_url": "https://www.fragrantica.com/perfume/AAP-PERFUMES/OUD-AMBER-72076.html",
    "fragrantica_rating": 0,
    "fragrantica_votes": 0,
    "main_accords": [],
    "top_notes": [],
    "heart_notes": [],
    "base_notes": [],
    "longevity": 0,
    "sillage": 0,
    "season_performance": null,
    "image_url": "/images/fragrances/72076.jpg",
    "brand_logo_url": null,
    "similar_scents": []
  },
  {
    "id": "frag-72085",
    "name": "",
    "brand": "",
    "slug": "",
    "year": null,
    "gender": null,
    "fragrance_family": null,
    "concentration": null,
    "description": "",
    "fragrantica_url": "https://www.fragrantica.com/perfume/AAP-PERFUMES/RENA-72085.html",
    "fragrantica_rating": 0,
    "fragrantica_votes": 0,
    "main_accords": [],
    "top_notes": [],
    "heart_notes": [],
    "base_notes": [],
    "longevity": 0,
    "sillage": 0,
    "season_performance": null,
    "image_url": "/images/fragrances/72085.jpg",
    "brand_logo_url": null,
    "similar_scents": []
  },
  {
    "id": "frag-72081",
    "name": "",
    "brand": "",
    "slug": "",
    "year": null,
    "gender": null,
    "fragrance_family": null,
    "concentration": null,
    "description": "",
    "fragrantica_url": "https://www.fragrantica.com/perfume/AAP-PERFUMES/SULTAN-72081.html",
    "fragrantica_rating": 0,
    "fragrantica_votes": 0,
    "main_accords": [],
    "top_notes": [],
    "heart_notes": [],
    "base_notes": [],
    "longevity": 0,
    "sillage": 0,
    "season_performance": null,
    "image_url": "/images/fragrances/72081.jpg",
    "brand_logo_url": null,
    "similar_scents": []
  },
  {
    "id": "frag-72083",
    "name": "",
    "brand": "",
    "slug": "",
    "year": null,
    "gender": null,
    "fragrance_family": null,
    "concentration": null,
    "description": "",
    "fragrantica_url": "https://www.fragrantica.com/perfume/AAP-PERFUMES/WHITE-OUD-72083.html",
    "fragrantica_rating": 0,
    "fragrantica_votes": 0,
    "main_accords": [],
    "top_notes": [],
    "heart_notes": [],
    "base_notes": [],
    "longevity": 0,
    "sillage": 0,
    "season_performance": null,
    "image_url": "/images/fragrances/72083.jpg",
    "brand_logo_url": null,
    "similar_scents": []
  },
  {
    "id": "frag-72074",
    "name": "",
    "brand": "",
    "slug": "",
    "year": null,
    "gender": null,
    "fragrance_family": null,
    "concentration": null,
    "description": "",
    "fragrantica_url": "https://www.fragrantica.com/perfume/AAP-PERFUMES/WILD-JASMINE-72074.html",
    "fragrantica_rating": 0,
    "fragrantica_votes": 0,
    "main_accords": [],
    "top_notes": [],
    "heart_notes": [],
    "base_notes": [],
    "longevity": 0,
    "sillage": 0,
    "season_performance": null,
    "image_url": "/images/fragrances/72074.jpg",
    "brand_logo_url": null,
    "similar_scents": []
  }
]