[
  {
    "id": "frag-109866",
    "name": "",
    "brand": "",
    "slug": "",
    "year": null,
    "gender": null,
    "fragrance_family": null,
    "concentration": null,
    "description": "",
    "fragrantica_url": "https://www.fragrantica.com/perfume/AAMO/Cherrynity-109866.html",
    "fragrantica_rating": 0,
    "fragrantica_votes": 0,
    "main_accords": [],
    "top_notes": [],
    "heart_notes": [],
    "base_notes": [],
    "longevity": 0,
    "sillage": 0,
    "season_performance": null,
    "image_url": "/images/fragrances/109866.jpg",
    "brand_logo_url": null,
    "similar_scents": []
  },
  {
    "id": "frag-109865",
    "name": "",
    "brand": "",
    "slug": "",
    "year": null,
    "gender": null,
    "fragrance_family": null,
    "concentration": null,
    "description": "",
    "fragrantica_url": "https://www.fragrantica.com/perfume/AAMO/Emit-Light-109865.html",
    "fragrantica_rating": 0,
    "fragrantica_votes": 0,
    "main_accords": [],
    "top_notes": [],
    "heart_notes": [],
    "base_notes": [],
    "longevity": 0,
    "sillage": 0,
    "season_performance": null,
    "image_url": "/images/fragrances/109865.jpg",
    "brand_logo_url": null,
    "similar_scents": []
  },
  {
    "id": "frag-109867",
    "name": "",
    "brand": "",
    "slug": "",
    "year": null,
    "gender": null,
    "fragrance_family": null,
    "concentration": null,
    "description": "",
    "fragrantica_url": "https://www.fragrantica.com/perfume/AAMO/Glace-Amor-109867.html",
    "fragrantica_rating": 0,
    "fragrantica_votes": 0,
    "main_accords": [],
    "top_notes": [],
    "heart_notes": [],
    "base_notes": [],
    "longevity": 0,
    "sillage": 0,
    "season_performance": null,
    "image_url": "/images/fragrances/109867.jpg",
    "brand_logo_url": null,
    "similar_scents": []
  },
  {
    "id": "frag-109868",
    "name": "",
    "brand": "",
    "slug": "",
    "year": null,
    "gender": null,
    "fragrance_family": null,
    "concentration": null,
    "description": "",
    "fragrantica_url": "https://www.fragrantica.com/perfume/AAMO/Unseen-109868.html",
    "fragrantica_rating": 0,
    "fragrantica_votes": 0,
    "main_accords": [],
    "top_notes": [],
    "heart_notes": [],
    "base_notes": [],
    "longevity": 0,
    "sillage": 0,
    "season_performance": null,
    "image_url": "/images/fragrances/109868.jpg",
    "brand_logo_url": null,
    "similar_scents": []
  }
]